pbshax/__init__.py
pbshax/_version.py
pbshax/main.py
pbshax/parallel.py
pbshax/regions.py
pbshax-0.1.2.dist-info/METADATA
pbshax-0.1.2.dist-info/WHEEL
pbshax-0.1.2.dist-info/entry_points.txt
pbshax-0.1.2.dist-info/top_level.txt
pbshax-0.1.2.dist-info/RECORD
